robotframework_pageobjects-1.3.3.dist-info/RECORD
robotframework_pageobjects-1.3.3.dist-info/WHEEL
robotframework_pageobjects-1.3.3.dist-info/metadata.json
robotframework_pageobjects-1.3.3.dist-info/DESCRIPTION.rst
robotframework_pageobjects-1.3.3.dist-info/METADATA
robotframework_pageobjects-1.3.3.dist-info/top_level.txt
robotpageobjects/sig.py
robotpageobjects/page.py
robotpageobjects/optionhandler.py
robotpageobjects/monkeypatches.py
robotpageobjects/exceptions.py
robotpageobjects/context.py
robotpageobjects/component.py
robotpageobjects/base.py
robotpageobjects/abstractedlogger.py
robotpageobjects/__init__.py
