Metadata-Version: 2.0
Name: robotframework-pageobjects
Version: 1.3.3
Summary: UNKNOWN
Home-page: UNKNOWN
Author: "National Center for Biotechnology Information"
Author-email: UNKNOWN
License: UNKNOWN
Keywords: "robotframework testing testautomation selenium selenium2 webdriver web"
Platform: UNKNOWN
Requires-Dist: decorator
Requires-Dist: mock (==1.0.1)
Requires-Dist: requests (==2.1.0)
Requires-Dist: robotframework-selenium2library (==1.7.2)
Requires-Dist: uritemplate (==0.6)
